ideeplc/__init__.py
ideeplc/__main__.py
ideeplc/calibrate.py
ideeplc/config.py
ideeplc/data_initialize.py
ideeplc/figure.py
ideeplc/fine_tuning.py
ideeplc/gui.py
ideeplc/ideeplc_core.py
ideeplc/model.py
ideeplc/predict.py
ideeplc/utilities.py
ideeplc/example_input/Hela_deeprt.csv
ideeplc/models/pretrained_model.pth
ideeplc/structure_feature/aa_stan.csv
ideeplc/structure_feature/ptm_stan.csv
ideeplc-1.3.0.dist-info/licenses/LICENSE
ideeplc-1.3.0.dist-info/METADATA
ideeplc-1.3.0.dist-info/WHEEL
ideeplc-1.3.0.dist-info/entry_points.txt
ideeplc-1.3.0.dist-info/top_level.txt
ideeplc-1.3.0.dist-info/RECORD
