Metadata-Version: 2.4
Name: ideeplc
Version: 1.3.0
Summary: iDeepLC: A deep Learning-based retention time predictor for unseen modified peptides with a novel encoding system
Author-email: Alireza Nameni <alireza.nameni@ugent.be>, Robbin Bouwmeester <robbin.bouwmeester@ugent.be>
License:                                  Apache License
Project-URL: GitHub, https://github.com/CompOmics/iDeepLC
Project-URL: CompOmics, https://www.compomics.com
Keywords: iDeepLC,deep learning,retention time,proteomics,peptide prediction
Classifier: Programming Language :: Python :: 3
Classifier: License :: OSI Approved :: Apache Software License
Classifier: Operating System :: OS Independent
Classifier: Programming Language :: Python :: 3 :: Only
Classifier: Topic :: Scientific/Engineering :: Bio-Informatics
Classifier: Development Status :: 5 - Production/Stable
Requires-Python: >=3.8
License-File: LICENSE
Requires-Dist: matplotlib<4,>=3.7
Requires-Dist: numpy<2,>=1.25
Requires-Dist: pandas<3,>=2
Requires-Dist: pyteomics<5,>=4.5
Requires-Dist: torch<3,>=2.2.1
Requires-Dist: scikit-learn<2,>=1.4
Requires-Dist: rich>=13
Requires-Dist: lxml<5,>=4.9
Provides-Extra: gui
Requires-Dist: pillow>=9.5; extra == "gui"
Requires-Dist: requests>=2.31; extra == "gui"
Provides-Extra: dev
Requires-Dist: pytest; extra == "dev"
Requires-Dist: pytest-cov; extra == "dev"
Requires-Dist: sphinx; extra == "dev"
Requires-Dist: black; extra == "dev"
Requires-Dist: flake8; extra == "dev"
Dynamic: license-file
